{
  "stats": {
    "suites": 1,
    "tests": 7,
    "passes": 7,
    "pending": 0,
    "failures": 0,
    "start": "2023-02-12T23:45:16.298Z",
    "end": "2023-02-12T23:46:19.101Z",
    "duration": 62803,
    "testsRegistered": 7,
    "passPercent": 100,
    "pendingPercent": 0,
    "other": 0,
    "hasOther": false,
    "skipped": 0,
    "hasSkipped": false
  },
  "results": [
    {
      "uuid": "554d71cd-435d-4223-9778-0ddf9a5291e0",
      "title": "",
      "fullFile": "cypress/integration/AllTests/PageObject_UpdateLoginScenario.js",
      "file": "cypress/integration/AllTests/PageObject_UpdateLoginScenario.js",
      "beforeHooks": [],
      "afterHooks": [],
      "tests": [],
      "suites": [
        {
          "uuid": "81aa3045-b453-4c76-858e-448fea0297eb",
          "title": "E2E_Testing",
          "fullFile": "",
          "file": "",
          "beforeHooks": [],
          "afterHooks": [],
          "tests": [
            {
              "title": "Login_Invalid userName",
              "fullTitle": "E2E_Testing Login_Invalid userName",
              "timedOut": null,
              "duration": 2678,
              "state": "passed",
              "speed": "fast",
              "pass": true,
              "fail": false,
              "pending": false,
              "context": null,
              "code": "",
              "err": {},
              "uuid": "146d0b64-96d8-476a-afff-025e8dfc52d7",
              "parentUUID": "81aa3045-b453-4c76-858e-448fea0297eb",
              "isHook": false,
              "skipped": false
            },
            {
              "title": "Login_Invalid Password",
              "fullTitle": "E2E_Testing Login_Invalid Password",
              "timedOut": null,
              "duration": 2290,
              "state": "passed",
              "speed": "fast",
              "pass": true,
              "fail": false,
              "pending": false,
              "context": null,
              "code": "",
              "err": {},
              "uuid": "250bc358-09ec-4e70-9bff-b2d07e372fde",
              "parentUUID": "81aa3045-b453-4c76-858e-448fea0297eb",
              "isHook": false,
              "skipped": false
            },
            {
              "title": "Login Valid Credentials",
              "fullTitle": "E2E_Testing Login Valid Credentials",
              "timedOut": null,
              "duration": 2355,
              "state": "passed",
              "speed": "fast",
              "pass": true,
              "fail": false,
              "pending": false,
              "context": null,
              "code": "",
              "err": {},
              "uuid": "6337bc97-0f97-4088-8b1a-3a94f5a82930",
              "parentUUID": "81aa3045-b453-4c76-858e-448fea0297eb",
              "isHook": false,
              "skipped": false
            },
            {
              "title": "Target_Flights_Page_Test",
              "fullTitle": "E2E_Testing Target_Flights_Page_Test",
              "timedOut": null,
              "duration": 25111,
              "state": "passed",
              "speed": "slow",
              "pass": true,
              "fail": false,
              "pending": false,
              "context": null,
              "code": "",
              "err": {},
              "uuid": "08a4615c-cd00-41ca-994c-a7db28fdeef2",
              "parentUUID": "81aa3045-b453-4c76-858e-448fea0297eb",
              "isHook": false,
              "skipped": false
            },
            {
              "title": "SMC_Flights_Page_Test",
              "fullTitle": "E2E_Testing SMC_Flights_Page_Test",
              "timedOut": null,
              "duration": 21154,
              "state": "passed",
              "speed": "slow",
              "pass": true,
              "fail": false,
              "pending": false,
              "context": null,
              "code": "",
              "err": {},
              "uuid": "4dcdfd0b-07d3-4d2e-822c-bd9cc12f54e3",
              "parentUUID": "81aa3045-b453-4c76-858e-448fea0297eb",
              "isHook": false,
              "skipped": false
            },
            {
              "title": "verifying Mission Details",
              "fullTitle": "E2E_Testing verifying Mission Details",
              "timedOut": null,
              "duration": 6138,
              "state": "passed",
              "speed": "medium",
              "pass": true,
              "fail": false,
              "pending": false,
              "context": null,
              "code": "",
              "err": {},
              "uuid": "10f08ffa-6454-4b31-9df8-c7aae7e86ea7",
              "parentUUID": "81aa3045-b453-4c76-858e-448fea0297eb",
              "isHook": false,
              "skipped": false
            },
            {
              "title": "logout_from_Application",
              "fullTitle": "E2E_Testing logout_from_Application",
              "timedOut": null,
              "duration": 2130,
              "state": "passed",
              "speed": "fast",
              "pass": true,
              "fail": false,
              "pending": false,
              "context": null,
              "code": "",
              "err": {},
              "uuid": "36306302-652e-44a5-a755-6625df708738",
              "parentUUID": "81aa3045-b453-4c76-858e-448fea0297eb",
              "isHook": false,
              "skipped": false
            }
          ],
          "suites": [],
          "passes": [
            "146d0b64-96d8-476a-afff-025e8dfc52d7",
            "250bc358-09ec-4e70-9bff-b2d07e372fde",
            "6337bc97-0f97-4088-8b1a-3a94f5a82930",
            "08a4615c-cd00-41ca-994c-a7db28fdeef2",
            "4dcdfd0b-07d3-4d2e-822c-bd9cc12f54e3",
            "10f08ffa-6454-4b31-9df8-c7aae7e86ea7",
            "36306302-652e-44a5-a755-6625df708738"
          ],
          "failures": [],
          "pending": [],
          "skipped": [],
          "duration": 61856,
          "root": false,
          "rootEmpty": false,
          "_timeout": 2000
        }
      ],
      "passes": [],
      "failures": [],
      "pending": [],
      "skipped": [],
      "duration": 0,
      "root": true,
      "rootEmpty": true,
      "_timeout": 2000
    }
  ],
  "meta": {
    "mocha": {
      "version": "7.0.1"
    },
    "mochawesome": {
      "options": {
        "quiet": false,
        "reportFilename": "[status]_[datetime]-[name]-report",
        "saveHtml": true,
        "saveJson": true,
        "consoleReporter": "spec",
        "useInlineDiffs": false,
        "code": false
      },
      "version": "7.1.3"
    },
    "marge": {
      "options": {
        "charts": true,
        "reportPageTitle": "Automation Report",
        "embeddedScreenshots": true,
        "inlineAssets": true,
        "reportFilename": "[status]_[datetime]-[name]-report",
        "code": "false",
        "autoOpen": "true",
        "overwrite": "false",
        "saveAllAttempts": false
      },
      "version": "6.2.0"
    }
  }
}